<Defs>
  <HediffDef>
    <defName>VU_SuccubusBond</defName>
    <label>psychic vampirism</label>
    <description>This person has a parasitic psychic bond with another person based on the psychic bonding gene.</description>
    <isBad>false</isBad>
    <everCurableByItem>false</everCurableByItem>
    <initialSeverity>1</initialSeverity>
    <stages>
      <li>
        <capMods>
          <li>
            <capacity>Consciousness</capacity>
            <offset>0.20</offset>
          </li>
        </capMods>
        <statOffsets>
          <BS_SoulPower>0.35</BS_SoulPower>
        </statOffsets>
      </li>
    </stages>
  </HediffDef>

  <HediffDef>
    <defName>VU_SuccubusBond_Victim</defName>
    <label>psychic vampirism victim</label>
    <description>This person is the target a parasitic psychic bond from another person based on the psychic bonding gene.</description>
    <isBad>false</isBad>
    <everCurableByItem>false</everCurableByItem>
    <initialSeverity>1</initialSeverity>
    <hediffClass>BigAndSmall.SuccubusBondVictim</hediffClass>
    <stages>
      <li>
        <capMods>
          <li>
            <capacity>Consciousness</capacity>
            <setMax>0.85</setMax>
          </li>
        </capMods>
        <statOffsets>
          <RestFallRateFactor>0.5</RestFallRateFactor>
          <BS_SoulPower>-0.4</BS_SoulPower>
        </statOffsets>
      </li>
      <li>
        <label>endured</label>
        <extraTooltip>Bond endured thanks to the psychic powers of the target.</extraTooltip>
        <minSeverity>1.5</minSeverity>
      </li>
    </stages>
  </HediffDef>

  <ThoughtDef>
    <defName>VU_SuccubusEuphoria</defName>
    <workerClass>ThoughtWorker_Hediff</workerClass>
    <hediff>VU_SuccubusBond_Victim</hediff>
    <validWhileDespawned>true</validWhileDespawned>
    <developmentalStageFilter>Baby, Child, Adult</developmentalStageFilter>
    <stages>
      <li>
        <label>succubus bond</label>
        <description>I'm fortunate to be with such a wonderful person.</description>
        <baseMoodEffect>20</baseMoodEffect>
      </li>
    </stages>
  </ThoughtDef>

  <HediffDef>
    <defName>VU_Euphoria</defName>
    <label>Euphoria</label>
    <description>A strange pleasant feeling.</description>
    <isBad>false</isBad>
    <everCurableByItem>false</everCurableByItem>
    <initialSeverity>1</initialSeverity>
    <hediffClass>HediffWithComps</hediffClass>
    <stages>
      <li>
        <capMods>
          <li>
            <capacity>Consciousness</capacity>
            <offset>-0.05</offset>
          </li>
        </capMods>
      </li>
    </stages>
    <comps>
      <!-- <li Class="HediffCompProperties_SeverityPerDay">
          <severityPerDay>-2.0</severityPerDay>
      </li> -->
      <li Class="HediffCompProperties_Disappears">
        <showRemainingTime>true</showRemainingTime>
        <disappearsAfterTicks>20000</disappearsAfterTicks>
      </li>
    </comps>
  </HediffDef>

  <ThoughtDef>
    <defName>VU_WhiteRoseEuphoria</defName>
    <workerClass>ThoughtWorker_Hediff</workerClass>
    <hediff>VU_Euphoria</hediff>
    <validWhileDespawned>true</validWhileDespawned>
    <developmentalStageFilter>Baby, Child, Adult</developmentalStageFilter>
    <stages>
      <li>
        <label>euphoria</label>
        <description>I'm feeling good.</description>
        <baseMoodEffect>20</baseMoodEffect>
      </li>
    </stages>
  </ThoughtDef>

  <HediffDef>
    <defName>VU_WhiteRoseBite</defName>
    <label>Mark of the Rose</label>
    <description>This person has recently been bitten by a white-rose vampire.</description>
    <isBad>false</isBad>
    <everCurableByItem>false</everCurableByItem>
    <initialSeverity>0.45</initialSeverity>
    <hediffClass>HediffWithComps</hediffClass>
    <stages>
      <li>
        <label>mind-wandering</label>
        <extraTooltip>I've been feeling a bit strange.</extraTooltip>
        <capMods>
          <li>
            <capacity>Consciousness</capacity>
            <offset>-0.01</offset>
          </li>
        </capMods>
      </li>
      <li>
        <label>intrusive thoughts</label>
        <extraTooltip>My thoughts keep drifting when I relax.</extraTooltip>
        <minSeverity>0.5</minSeverity>
        <capMods>
          <li>
            <capacity>Consciousness</capacity>
            <offset>-0.05</offset>
          </li>
        </capMods>
      </li>
      <li>
        <label>obsessive thought-patterns</label>
        <extraTooltip>I keep losing my focus.</extraTooltip>
        <minSeverity>0.7</minSeverity>
        <capMods>
          <li>
            <capacity>Consciousness</capacity>
            <offset>-0.10</offset>
          </li>
        </capMods>
      </li>
    </stages>
    <comps>
      <li Class="HediffCompProperties_SeverityPerDay">
        <severityPerDay>-0.1</severityPerDay>
        <showHoursToRecover>true</showHoursToRecover>
      </li>
    </comps>
  </HediffDef>
  <HediffDef>
    <defName>VU_WhiteRoseThrall</defName>
    <label>Servant of the Rose</label>
    <description>This person has been reapeatedly fed on by a white-rose vampire.</description>
    <isBad>false</isBad>
    <everCurableByItem>false</everCurableByItem>
    <initialSeverity>1.0</initialSeverity>
    <maxSeverity>1.1</maxSeverity>
    <hediffClass>HediffWithComps</hediffClass>
    <stages>
      <li>
        <label>crumbling bond</label>
        <capMods>
          <li>
            <capacity>Consciousness</capacity>
            <offset>-0.05</offset>
          </li>
        </capMods>
        <statFactors>
          <GlobalLearningFactor>0.95</GlobalLearningFactor>
          <MoveSpeed>1.02</MoveSpeed>
          <WorkSpeedGlobal>0.9</WorkSpeedGlobal>
          <MeleeDamageFactor>1.12</MeleeDamageFactor>
          <RestFallRateFactor>1.3</RestFallRateFactor>
        </statFactors>
        <statOffsets>
          <SlaveSuppressionOffset MayRequire="Ludeon.RimWorld.Ideology">-0.15</SlaveSuppressionOffset>
        </statOffsets>
      </li>
      <li>
        <label>weakening bond</label>
        <extraTooltip>I feel deflated.</extraTooltip>
        <minSeverity>0.50</minSeverity>
        <capMods>
          <li>
            <capacity>Consciousness</capacity>
            <offset>-0.20</offset>
          </li>
        </capMods>
        <statFactors>
          <GlobalLearningFactor>0.75</GlobalLearningFactor>
          <MoveSpeed>0.8</MoveSpeed>
        </statFactors>
        <statOffsets>
          <SlaveSuppressionOffset MayRequire="Ludeon.RimWorld.Ideology">0.05</SlaveSuppressionOffset>
        </statOffsets>
      </li>
      <li>
        <label>strong bond</label>
        <extraTooltip>The bond is strong and I feel a strange drive and vigor.</extraTooltip>
        <minSeverity>0.70</minSeverity>
        <capMods>
          <li>
            <capacity>Consciousness</capacity>
            <offset>-0.10</offset>
          </li>
        </capMods>
        <statFactors>
          <GlobalLearningFactor>0.65</GlobalLearningFactor>
          <MoveSpeed>1.10</MoveSpeed>
          <WorkSpeedGlobal>1.35</WorkSpeedGlobal>
          <MeleeDamageFactor>1.15</MeleeDamageFactor>
          <SlaveSuppressionFallRate MayRequire="Ludeon.RimWorld.Ideology">0</SlaveSuppressionFallRate>
          <!-- <RestFallRateFactor>0.5</RestFallRateFactor> -->
        </statFactors>
        <statOffsets>
          <SlaveSuppressionOffset MayRequire="Ludeon.RimWorld.Ideology">0.20</SlaveSuppressionOffset>
        </statOffsets>
        <painOffset>-0.25</painOffset>
      </li>
    </stages>
    <comps>
      <li Class="HediffCompProperties_SeverityPerDay">
        <severityPerDay>-0.08</severityPerDay>
        <showHoursToRecover>true</showHoursToRecover>
      </li>
    </comps>
  </HediffDef>

  <ThoughtDef>
    <defName>VU_ThrallEuphoria</defName>
    <workerClass>ThoughtWorker_Hediff</workerClass>
    <hediff>VU_WhiteRoseThrall</hediff>
    <validWhileDespawned>true</validWhileDespawned>
    <developmentalStageFilter>Baby, Child, Adult</developmentalStageFilter>
    <stages>
      <li>
        <label>crumbling bond</label>
        <description>I feel horrible, but I also feel like my thouhts are becoming my own again.</description>
        <baseMoodEffect>-20</baseMoodEffect>
      </li>
      <li>
        <label>weakening bond</label>
        <description>I feel strange... weak... and uneasy...</description>
        <baseMoodEffect>-5</baseMoodEffect>
      </li>
      <li>
        <label>strong bond</label>
        <description>I'm safe under their protection.</description>
        <baseMoodEffect>12</baseMoodEffect>
      </li>
    </stages>
  </ThoughtDef>

  <HediffDef>
    <defName>VU_DraculVampirism</defName>
    <label>Vampirism</label>
    <description>This person has recently been infected by vampirism from a Dracul or Draculina. It is crucial that they get medical treatment quick.</description>
    <isBad>true</isBad>
    <makesSickThought>true</makesSickThought>
    <lethalSeverity>1</lethalSeverity>
    <tendable>true</tendable>
    <initialSeverity>0.01</initialSeverity>
    <hediffClass>BigAndSmall.DraculVampirism</hediffClass>
    <stages>
      <li>
        <label>weakened</label>
        <extraTooltip>I feel a bit lethargic and unfocused.</extraTooltip>
        <capMods>
          <li>
            <capacity>Consciousness</capacity>
            <offset>-0.10</offset>
          </li>
        </capMods>
        <painOffset>0.05</painOffset>
        <statFactors>
          <RestFallRateFactor>1.2</RestFallRateFactor>
        </statFactors>
      </li>
      <li>
        <label>drained</label>
        <extraTooltip>I feel seriously ill.</extraTooltip>
        <minSeverity>0.25</minSeverity>
        <capMods>
          <li>
            <capacity>Consciousness</capacity>
            <offset>-0.15</offset>
          </li>
        </capMods>
        <painOffset>0.35</painOffset>
        <statFactors>
          <RestFallRateFactor>1.4</RestFallRateFactor>
        </statFactors>
      </li>
      <li>
        <label>signs of infection</label>
        <extraTooltip>I feel a bit ill, but nothing that would hold me back.</extraTooltip>
        <minSeverity>0.50</minSeverity>
        <capMods>
          <li>
            <capacity>Consciousness</capacity>
            <offset>-0.20</offset>
          </li>
        </capMods>
        <painOffset>0.05</painOffset>
        <statFactors>
          <GlobalLearningFactor>0.85</GlobalLearningFactor>
          <MoveSpeed>1.10</MoveSpeed>
          <WorkSpeedGlobal>0.95</WorkSpeedGlobal>
          <MeleeDamageFactor>1.20</MeleeDamageFactor>
          <RestFallRateFactor>1.45</RestFallRateFactor>
        </statFactors>
      </li>
      <li>
        <label>infected</label>
        <extraTooltip>Feels like I need to sleep a bit more than usual, but otherwise I'm okay. I feel quite energized actually.</extraTooltip>
        <minSeverity>0.60</minSeverity>
        <capMods>
          <li>
            <capacity>Consciousness</capacity>
            <offset>-0.20</offset>
          </li>
        </capMods>
        <painOffset>-0.10</painOffset>
        <statFactors>
          <GlobalLearningFactor>0.55</GlobalLearningFactor>
          <MoveSpeed>1.15</MoveSpeed>
          <WorkSpeedGlobal>0.80</WorkSpeedGlobal>
          <MeleeDamageFactor>1.20</MeleeDamageFactor>
          <RestFallRateFactor>1.45</RestFallRateFactor>
        </statFactors>
      </li>
      <li>
        <label>turning</label>
        <extraTooltip>Feels like I need to sleep a lot, but otherwise I'm okay. When I'm not resting I feel healthy and full of energy.</extraTooltip>
        <minSeverity>0.80</minSeverity>
        <!-- <lifeThreatening>true</lifeThreatening> -->
        <capMods>
          <li>
            <capacity>Consciousness</capacity>
            <offset>-0.05</offset>
          </li>
        </capMods>
        <painOffset>-0.30</painOffset>
        <statFactors>
          <GlobalLearningFactor>0.15</GlobalLearningFactor>
          <MoveSpeed>1.20</MoveSpeed>
          <WorkSpeedGlobal>0.75</WorkSpeedGlobal>
          <MeleeDamageFactor>1.35</MeleeDamageFactor>
          <RestFallRateFactor>1.6</RestFallRateFactor>
        </statFactors>
      </li>
    </stages>
    <comps>
      <li Class="HediffCompProperties_TendDuration">
        <baseTendDurationHours>10</baseTendDurationHours>
        <severityPerDayTended>-0.5</severityPerDayTended>
      </li>
      <li Class="HediffCompProperties_Immunizable">
        <severityPerDayNotImmune>0.4</severityPerDayNotImmune>
        <immunityPerDaySick>0.38</immunityPerDaySick>
        <severityPerDayImmune>-0.5</severityPerDayImmune>
        <immunityPerDayNotSick>-1.0</immunityPerDayNotSick>
      </li>
    </comps>
  </HediffDef>

  <HediffDef>
    <defName>VU_DraculAge</defName>
    <label>Dracul Maturity</label>
    <description>How close this person is to reaching the next stage of Dracul vampirism.\n\nSlaves, prisoners will be unable to increase stage nor will colonists in involuntary deathrest.\n\nA minimum of 75% Hemogen is also needed.</description>
    <isBad>false</isBad>
    <everCurableByItem>false</everCurableByItem>
    <hediffClass>BigAndSmall.DraculStageProgression</hediffClass>
    <comps>
      <!-- <li Class="HediffCompProperties_SeverityPerDay">
          <severityPerDay>-2.0</severityPerDay>
      </li> -->
      <li Class="HediffCompProperties_Disappears">
        <showRemainingTime>true</showRemainingTime>
        <disappearsAfterTicks>15000</disappearsAfterTicks>
      </li>
    </comps>
  </HediffDef>

  <HediffDef>
    <defName>VU_DraculAnimalVampirism</defName>
    <label>Vampiric Ressurection</label>
    <description>This animal has risen from the dead to a semi-living state under the command of a vampire.</description>
    <extraTooltip>Greatly decreases bleeding rate.</extraTooltip>
    <isBad>false</isBad>
    <makesSickThought>false</makesSickThought>
    <everCurableByItem>false</everCurableByItem>
    <stages>
      <li>
        <!-- <label>turning</label>
        <minSeverity>0.80</minSeverity> -->
        <!-- <lifeThreatening>true</lifeThreatening> -->
        <capMods>
          <li>
            <capacity>Consciousness</capacity>
            <offset>-0.20</offset>
          </li>
        </capMods>
        <hungerRateFactorOffset>0.5</hungerRateFactorOffset>
        <painOffset>-5.0</painOffset>
        <statFactors>
          <!-- <BleedingRate>0</BleedingRate> -->
          <MoveSpeed>1.15</MoveSpeed>
          <MeleeDamageFactor>1.15</MeleeDamageFactor>
          <RestFallRateFactor>1.5</RestFallRateFactor>
          <InjuryHealingFactor>0.9</InjuryHealingFactor>
          <SM_BulletDmgMult>0.80</SM_BulletDmgMult>
        </statFactors>
        <statOffsets>
          <ToxicResistance>2</ToxicResistance>
        </statOffsets>
      </li>
    </stages>
    <comps>
    </comps>
  </HediffDef>

  <HediffDef>
    <defName>VU_AnimalReturned</defName>
    <label>Returned</label>
    <description>This animal has risen from the dead as an undead anomality.</description>
    <extraTooltip>Prevents bleeding.</extraTooltip>
    <isBad>false</isBad>
    <makesSickThought>false</makesSickThought>
    <everCurableByItem>false</everCurableByItem>
    <stages>
      <li>
        <!-- <label>turning</label>
        <minSeverity>0.80</minSeverity> -->
        <!-- <lifeThreatening>true</lifeThreatening> -->
        <capMods>
          <li>
            <capacity>Consciousness</capacity>
            <offset>-0.10</offset>
          </li>
        </capMods>
        <hungerRateFactorOffset>-0.5</hungerRateFactorOffset>
        <painOffset>-10.0</painOffset>
        <statFactors>
          <!-- <BleedingRate>0</BleedingRate> -->
          <MoveSpeed>0.90</MoveSpeed>
          <MeleeDamageFactor>0.90</MeleeDamageFactor>
          <IncomingDamageFactor>0.75</IncomingDamageFactor>
          <RestFallRateFactor>1.5</RestFallRateFactor>
          <InjuryHealingFactor>0.35</InjuryHealingFactor>
          <SM_BulletDmgMult>0.35</SM_BulletDmgMult>
          <Fertility>0</Fertility>
        </statFactors>
        <statOffsets>
          <ToxicResistance>2</ToxicResistance>
        </statOffsets>
      </li>
    </stages>
    <comps>
    </comps>
  </HediffDef>

  <HediffDef>
    <defName>BS_ReturnedReanimation</defName>
    <label>returning</label>
    <description>You shouldn't be able to see this.</description>
    <isBad>true</isBad>
    <makesSickThought>true</makesSickThought>
    <lethalSeverity>1</lethalSeverity>
    <tendable>true</tendable>
    <initialSeverity>0.01</initialSeverity>
    <hediffClass>BigAndSmall.VUReturning</hediffClass>
    <stages>
      <li>
        <label>hmm...</label>
        <becomeVisible>false</becomeVisible>
      </li>
    </stages>
  </HediffDef>
<!-- 
  <MentalStateDef ParentName="BaseMentalState">
    <defName>BS_ZombieBerserk</defName>
    <stateClass>BigAndSmall.MentalState_ReturnedBerserk</stateClass>
    <label>berserk</label>
    <category>Aggro</category>
    <blockInteractionInitiationExcept>
      <li>Insult</li>
    </blockInteractionInitiationExcept>
    <blockInteractionRecipientExcept>
      <li>Insult</li>
    </blockInteractionRecipientExcept>
    <blockRandomInteraction>true</blockRandomInteraction>
    <moodRecoveryThought>Catharsis</moodRecoveryThought>
    <blockNormalThoughts>true</blockNormalThoughts>
    <nameColor>(0.9,0.2,0.5)</nameColor>
    <beginLetter>{0} has gone berserk.\n\n[PAWN_pronoun] will attack anyone living [PAWN_pronoun] sees.</beginLetter>
    <beginLetterDef>ThreatSmall</beginLetterDef>
    <minTicksBeforeRecovery>40000</minTicksBeforeRecovery>
    <maxTicksBeforeRecovery>60000</maxTicksBeforeRecovery>
    <recoveryMtbDays>0.25</recoveryMtbDays>
    <recoveryMessage>{0}'s berserk rage has come to an end.</recoveryMessage>
    <baseInspectLine>Mental state: Berserk</baseInspectLine>
    <stateEffecter>Berserk</stateEffecter>
    <tale>MentalStateBerserk</tale>
    <recoverFromSleep>true</recoverFromSleep>
    <inCaravanCanDo>true</inCaravanCanDo>
  </MentalStateDef> -->

</Defs>